rfp_betterment_analyzer/__init__.py
rfp_betterment_analyzer/analyzer.py
rfp_betterment_analyzer/cli.py
rfp_betterment_analyzer/models.py
rfp_betterment_analyzer/utils.py
rfp_betterment_analyzer-1.0.0.dist-info/METADATA
rfp_betterment_analyzer-1.0.0.dist-info/WHEEL
rfp_betterment_analyzer-1.0.0.dist-info/entry_points.txt
rfp_betterment_analyzer-1.0.0.dist-info/top_level.txt
rfp_betterment_analyzer-1.0.0.dist-info/RECORD
