Metadata-Version: 2.4
Name: rfp-betterment-analyzer
Version: 1.0.0
Summary: A tool to evaluate proposal content and identify betterments for U.S. Government RFP responses
Home-page: https://github.com/rfpanalysis/rfp-betterment-analyzer
Author: RFP Analysis Team
Author-email: info@rfpanalysis.example.com
Classifier: Programming Language :: Python :: 3
Classifier: Programming Language :: Python :: 3.8
Classifier: Programming Language :: Python :: 3.9
Classifier: Programming Language :: Python :: 3.10
Classifier: License :: OSI Approved :: MIT License
Classifier: Operating System :: OS Independent
Classifier: Topic :: Office/Business
Classifier: Topic :: Text Processing :: Markup
Classifier: Intended Audience :: Developers
Classifier: Intended Audience :: Information Technology
Classifier: Intended Audience :: Other Audience
Requires-Python: >=3.8
Requires-Dist: nltk>=3.6.0
Requires-Dist: scikit-learn>=0.24.0
Requires-Dist: pandas>=1.2.0
Requires-Dist: tqdm>=4.62.0
Dynamic: author
Dynamic: author-email
Dynamic: classifier
Dynamic: description
Dynamic: description-content-type
Dynamic: home-page
Dynamic: requires-dist
Dynamic: requires-python
Dynamic: summary
